kiarina/lib/falkordb/__init__.py
kiarina/lib/falkordb/_settings.py
kiarina/lib/falkordb/asyncio.py
kiarina/lib/falkordb/py.typed
kiarina/lib/falkordb/_async/__init__.py
kiarina/lib/falkordb/_async/helpers/__init__.py
kiarina/lib/falkordb/_async/helpers/get_falkordb.py
kiarina/lib/falkordb/_core/__init__.py
kiarina/lib/falkordb/_core/helpers/__init__.py
kiarina/lib/falkordb/_core/helpers/get_falkordb.py
kiarina/lib/falkordb/_sync/__init__.py
kiarina/lib/falkordb/_sync/helpers/__init__.py
kiarina/lib/falkordb/_sync/helpers/get_falkordb.py
kiarina_lib_falkordb-1.35.0.dist-info/METADATA
kiarina_lib_falkordb-1.35.0.dist-info/WHEEL
kiarina_lib_falkordb-1.35.0.dist-info/RECORD
